LICENSE.txt
README.rst
setup.py
epub_extractor/__init__.py
epub_extractor/epub_dump_meta.py
epub_extractor/epub_dump_toc.py
epub_extractor/epub_extract_jpeg.py
epub_extractor/epub_extractor.py
epub_extractor/~test_epub_dump_meta.py
epub_extractor/~test_epub_dump_toc.py
epub_extractor/~test_extract_epub.py
epub_extractor.egg-info/PKG-INFO
epub_extractor.egg-info/SOURCES.txt
epub_extractor.egg-info/dependency_links.txt
epub_extractor.egg-info/entry_points.txt
epub_extractor.egg-info/top_level.txt